{
    "lesson8": {
        "title": "सूरजकुंड मेला",
        "questions": [
            {
                "q": "अंकन के पत्र का मुख्य उद्देश्य क्या था ?",
                "a": "अंकन के पत्र का मुख्य उद्देश्य हस्तशिल्प मेला का वर्ण करना। इन वस्तुओं से हम अपनी सभ्यता और संस्कृति की जानकारी प्राप्त होती है!"
            },
            {
                "q": "उद्योग मेलों से हंमे क्या जानकारी मिलती है?",
                "a": "उद्योग मेलों दूरा हमे विभिन्न प्रदेशों की कला और संस्कृति की जानकारी प्राप्त होती है !"
            },
            {
                "q": "उद्योग मेलों में क्या दर्शाया जाता है?",
                "a": "उद्योग मेलों में हात की बनी हुई चीजें, खिलौना, सुंदर मूर्तियाँ, ठप्पे और तांबे की बनी वस्तुयें और प्रदेश विशेष की कला दर्शाया जाती है!"
            },
            {
                "q": "मेलों से क्या-क्या लाभ है ?",
                "a": "मेलो विविधता में एकता स्थापित करते हैं! ये प्रत्येक प्रदेश को कला संस्कृति केमाध्यम से एक दूसरे के पास लाते हैं और विभिन्न कलाओं कों लोकप्रियता दिलवाते हैं !"
            }
        ],
        "fillblanks": [
            {
                "q": "combined example: <strong class=\"underline\">important and underlined</strong>",
                "a": "नमस्ते"
            }
        ],
        "meanings": [
            {
                "q": "आमंत्रित ",
                "a": "निमंत्रण देना "
            },
            {
                "q": "आयोजन ",
                "a": "प्रबंध "
            },
            {
                "q": "वास्तुकला ",
                "a": "भवन निर्माण की कला "
            }, 
            {
                "q": "सभ्यता ",
                "a": "समाज की उन्नति "
            },
            {
                "q": "शिल्पियों ",
                "a": "कारीगरों "
            },
            {
                "q": "कार्य - कुशलता ",
                "a": "कार्य को भली-भाति करना "
            },
            {
                "q": "उजागर ",
                "a": "प्रकट "
            },
            {
                "q": "प्रांतों ",
                "a": "प्रदेशों "
            },
            {
                "q": "विविधता ",
                "a": "अनेकता, कई तरह का "
            },
            {
                "q": "प्रोस्ताहन ",
                "a": "उत्साह बढ़ाना "
            },
            {
                "q": "संस्कृति ",
                "a": "संस्कारों से प्राप्त "
            },
            {
                "q": "समारोह ",
                "a": "उत्सव, मेला "
            }
        ]
    },
    "lesson9": {
        "title": "सुमन एक उपवन के ",
        "questions": [
            {
                "q": "हम सब कवि ने किसके लिए कहा है?",
                "a": "कवि ने हम फूलों केलिए है यहाँ उसका अर्ध भारत के निवासियों से है ।"
            },
            {
                "q": "फूलों को खिलाने के लिए क्या-क्या चाहिए ",
                "a": "फूलों को खिलाने केलिए मिट्टी, हवा, जल और सूर्या की रोशनी चाहिए ।"
            },
            {
                "q": "उपवन को शोभा किन से होती हैं?",
                "a": "उपवन को शोभा फूलों से होती है।"
            },
            {
                "q": "फूल क्या कहना चाह रहे हैं ?",
                "a": "फूल क्या कहना चाह रहे है कि हम कठिनाइयों में भी हसते रहते है, हम सभी को बिना किसी भेद-भाव के अपनी सुगंध देते है तदा सभी को सुंदर बनते है ।"
            },
            {
                "q": "इन कविता का संदेश को अपने शब्दों में लिखो ",
                "a": "यह कविता हमे संदेश देती है कि भारत में रहनेवाला हर मनुष्य चाहे वह किसी भी धर्म जाति या रंग-रूप का हो, एक दूसरे से मित्रता के सूत्र में बंधा है । इससे ही भारत की शोभा है ।"
            }
        ],
        "fillblanks": [
            {
                "q": "combined example: <strong class=\"underline\">important and underlined</strong>",
                "a": "नमस्ते"
            }
        ],
        "meanings": [
            {
                "q": "सुमन ",
                "a": "फूल "
            },
            {
                "q": "पले ",
                "a": "पालन - पोषण हुअ "
            },
            {
                "q": "पलना ",
                "a": "झूलों "
            },
            {
                "q": "उर ",
                "a": "हृदय - दिल "
            },
            {
                "q": "भ्रमरों ",
                "a": "भँवरों "
            },
            {
                "q": "गुंजन ",
                "a": "भँवरों की गुन-गुन आवाज़ "
            },
            {
                "q": "शोभा ",
                "a": "सुंदरता "
            },
            {
                "q": "गगन ",
                "a": "आकाश "
            },
            {
                "q": "सूत्र ",
                "a": "धागा "
            },
            {
                "q": "शृंगार ",
                "a": "सजावट , आभूषण "
            }
        ]
    }
}